mysql2md/__init__.py
mysql2md/mysql2md.py
mysql2md-0.0.6.dist-info/METADATA
mysql2md-0.0.6.dist-info/WHEEL
mysql2md-0.0.6.dist-info/top_level.txt
mysql2md-0.0.6.dist-info/RECORD
