Metadata-Version: 2.1
Name: mysql2md
Version: 0.0.6
Summary: 根据mysql表结构生成markdown文档
Home-page: UNKNOWN
Author: guoridgepole
Author-email: UNKNOWN
License: MIT Licence
Platform: any
Requires-Dist: pymysql
Requires-Dist: argparse
